{
  "ctx": "tokenizer_info",
  "licoes": [
    {
      "erro": "arquitetura_llama",
      "causa": "conceito: arquitetura_llama",
      "solucao": "Modelo: sha256-f5074b122, tamanho: 4.07GB, tokens: 32768, merges: 0",
      "ctx": "tokenizer_info",
      "tipo": "dominio",
      "time_sensitive": false,
      "tags": [],
      "timestamp": 1782910027.6509545,
      "id": "L0857",
      "inactive": true
    },
    {
      "erro": "arquitetura_llama",
      "causa": "conceito: arquitetura_llama",
      "solucao": "Modelo: sha256-f5074b122, tamanho: 4.07GB, tokens: 32768, merges: 0",
      "ctx": "tokenizer_info",
      "tipo": "dominio",
      "time_sensitive": false,
      "tags": [],
      "timestamp": 1782910277.1483822,
      "id": "L0898"
    }
  ]
}